drf_tracking_logstash/__init__.py
drf_tracking_logstash/base_mixins.py
drf_tracking_logstash/mixins.py
drf_tracking_logstash-1.2.dist-info/DESCRIPTION.rst
drf_tracking_logstash-1.2.dist-info/METADATA
drf_tracking_logstash-1.2.dist-info/RECORD
drf_tracking_logstash-1.2.dist-info/WHEEL
drf_tracking_logstash-1.2.dist-info/metadata.json
drf_tracking_logstash-1.2.dist-info/top_level.txt
