Metadata-Version: 2.0
Name: drf-tracking-logstash
Version: 1.2
Summary: Log requests on logstash
Home-page: https://github.com/singhravi1/drf-tracking-logstash
Author: Ravi Singh
Author-email: ravisinghofficial@gmail.com
License: UNKNOWN
Platform: UNKNOWN
Classifier: Programming Language :: Python :: 3
Classifier: Operating System :: OS Independent
